phones/__init__.py
phones/convert.py
phones/features.py
phones/normalize.py
phones/phonecodes/.git
phones/phonecodes/.gitignore
phones/phonecodes/LICENSE.txt
phones/phonecodes/README.md
phones/phonecodes/src/__init__.py
phones/phonecodes/src/feature_tables.txt
phones/phonecodes/src/phonecode_tables.py
phones/phonecodes/src/phonecodes.py
phones/phonecodes/src/pronlex.py
phones/phonecodes/src/underspecification_rules.txt
phones/phonecodes/test/fixtures/babel_amh_ipa.txt
phones/phonecodes/test/fixtures/babel_amh_sample.txt
phones/phonecodes/test/fixtures/babel_amh_xsampa.txt
phones/phonecodes/test/fixtures/babel_ben_ipa.txt
phones/phonecodes/test/fixtures/babel_ben_sample.txt
phones/phonecodes/test/fixtures/babel_ben_xsampa.txt
phones/phonecodes/test/fixtures/callhome_arz_callhome.txt
phones/phonecodes/test/fixtures/callhome_arz_ipa.txt
phones/phonecodes/test/fixtures/callhome_arz_sample.txt
phones/phonecodes/test/fixtures/callhome_arz_xsampa.txt
phones/phonecodes/test/fixtures/callhome_cmn_callhome.txt
phones/phonecodes/test/fixtures/callhome_cmn_ipa.txt
phones/phonecodes/test/fixtures/callhome_cmn_sample.txt
phones/phonecodes/test/fixtures/callhome_cmn_xsampa.txt
phones/phonecodes/test/fixtures/callhome_spa_callhome.txt
phones/phonecodes/test/fixtures/callhome_spa_ipa.txt
phones/phonecodes/test/fixtures/callhome_spa_sample.txt
phones/phonecodes/test/fixtures/callhome_spa_xsampa.txt
phones/phonecodes/test/fixtures/celex_deu_disc.txt
phones/phonecodes/test/fixtures/celex_deu_ipa.txt
phones/phonecodes/test/fixtures/celex_deu_sample.txt
phones/phonecodes/test/fixtures/celex_deu_sample_ipa.txt
phones/phonecodes/test/fixtures/celex_deu_xsampa.txt
phones/phonecodes/test/fixtures/celex_eng_arpabet.txt
phones/phonecodes/test/fixtures/celex_eng_disc.txt
phones/phonecodes/test/fixtures/celex_eng_ipa.txt
phones/phonecodes/test/fixtures/celex_eng_sample.txt
phones/phonecodes/test/fixtures/celex_eng_xsampa.txt
phones/phonecodes/test/fixtures/celex_nld_disc.txt
phones-0.0.7.dist-info/WHEEL
phones-0.0.7.dist-info/METADATA
phones-0.0.7.dist-info/licenses/LICENSE
phones-0.0.7.dist-info/RECORD
