Metadata-Version: 2.1
Name: phones
Version: 0.0.7
Summary: A collection of utilities for handling IPA phones.
License: MIT
Author-email: Christoph Minixhofer <christoph.minixhofer@gmail.com>
Requires-Python: >=3.8,<3.11
Requires-Dist: numpy>=1.24.4
Requires-Dist: pandas>=2.0.3
Requires-Dist: scipy>=1.10.1
Requires-Dist: tqdm>=4.66.1
Provides-Extra: plots
Requires-Dist: plotly>=5.5.0; extra == "plots"
Requires-Dist: scikit-learn>=0.24.2; extra == "plots"
Provides-Extra: test
Requires-Dist: pytest>=7.0.0; extra == "test"
Requires-Dist: pytest-cov>=3.0.0; extra == "test"
Project-URL: homepage, https://cdminix.me/phones
